py_directus/__init__.py
py_directus/aggregator.py
py_directus/cache.py
py_directus/directus.py
py_directus/directus_request.py
py_directus/directus_response.py
py_directus/expression.py
py_directus/fast_api/__init__.py
py_directus/fast_api/auth.py
py_directus/fast_api/exceptions.py
py_directus/fast_api/lifespan.py
py_directus/fast_api/utils.py
py_directus/filter.py
py_directus/models/__init__.py
py_directus/models/base.py
py_directus/models/directus.py
py_directus/models/types.py
py_directus/operators.py
py_directus/storage.py
py_directus/transformation.py
py_directus/utils.py
py_directus2-0.0.31.dist-info/WHEEL
py_directus2-0.0.31.dist-info/METADATA
py_directus2-0.0.31.dist-info/RECORD
