Metadata-Version: 2.3
Name: py-directus2
Version: 0.0.31
Summary: Python wrapper for asynchronous interaction with Directus
Keywords: python,directus,async,asyncio,api,wrapper
Author: Panos Stavrianos
Author-email: Panos Stavrianos <panos@orbitsystems.gr>
License: MIT
Requires-Dist: aiofiles>=23.2.1
Requires-Dist: httpx>=0.25.0,<1.0.0
Requires-Dist: json-fix>=0.5.2,<1.0.0
Requires-Dist: python-dotenv>=1.0.0,<2.0.0
Requires-Dist: python-magic>=0.4.27,<1.0.0
Requires-Dist: pydantic>2.0
Requires-Dist: rich>=13.6.0,<14.0.0
Requires-Dist: websockets>=11.0.3
Requires-Dist: platformdirs
Requires-Dist: anyio>=3.7.1,<4.0.0 ; extra == 'fastapi'
Requires-Dist: fastapi ; extra == 'fastapi'
Requires-Dist: starlette ; extra == 'fastapi'
Maintainer: Rafał Krupiński
Maintainer-email: Rafał Krupiński <oeklo.it@fastmail.com>
Requires-Python: >=3.10
Project-URL: Documentation, https://oeklo.github.com/py-directus
Provides-Extra: fastapi
